context_temp.py
context_temp-0.11.2.dist-info/LICENSE
context_temp-0.11.2.dist-info/METADATA
context_temp-0.11.2.dist-info/WHEEL
context_temp-0.11.2.dist-info/top_level.txt
context_temp-0.11.2.dist-info/RECORD
